osmxml/__init__.py
osmxml/attribute.py
osmxml/element.py
osmxml/parser.py
osmxml/text.py
osmxml/xml.py
osmxml-1.0.1.dist-info/METADATA
osmxml-1.0.1.dist-info/WHEEL
osmxml-1.0.1.dist-info/top_level.txt
osmxml-1.0.1.dist-info/RECORD
