Metadata-Version: 2.4
Name: osmxml
Version: 1.0.1
Summary: Python object-oriented xml package
Author: osmiumnet
Requires-Python: >=3.10
Dynamic: author
Dynamic: requires-python
